{
  "name": "Space",
  "fields": [
    {
      "fieldName": "name",
      "fieldType": "String",
      "fieldValidateRules": ["required"]
    },
    {
      "fieldName": "active",
      "fieldType": "Boolean"
    },
    {
      "fieldName": "reference",
      "fieldType": "String",
      "fieldValidateRules": ["required", "unique"]
    },
    {
      "fieldName": "description",
      "fieldType": "String"
    },
    {
      "fieldName": "maxPhotos",
      "fieldType": "Integer"
    },
    {
      "fieldName": "visible",
      "fieldType": "Boolean"
    }
  ],
  "relationships": [
    {
      "relationshipType": "one-to-many",
      "otherEntityName": "photo",
      "otherEntityRelationshipName": "space",
      "relationshipValidateRules": "required",
      "relationshipName": "photo",
      "otherEntityField": "name"
    },
    {
      "relationshipType": "many-to-one",
      "otherEntityName": "company",
      "otherEntityRelationshipName": "space",
      "relationshipValidateRules": "required",
      "relationshipName": "company",
      "otherEntityField": "cif"
    }
  ],
  "entityTableName": "space",
  "dto": "mapstruct",
  "pagination": "no",
  "service": "serviceImpl",
  "jpaMetamodelFiltering": true,
  "fluentMethods": true,
  "readOnly": false,
  "embedded": false,
  "applications": ["ShopTheLook"],
  "changelogDate": "20210625180854"
}
